{"name":"User opens the mDL document from the dashboard","id":"view-mdl-document;user-opens-the-mdl-document-from-the-dashboard","scenarioId":"ios/regressionTests/view_mdl:User opens the mDL document from the dashboard","methodName":"User opens the mDL document from the dashboard","testSteps":[{"number":1,"description":"Given the user is on the dashboard screen","duration":12330,"startTime":"2024-10-08T15:58:07.455006+03:00[Europe/Athens]","result":"SUCCESS","precondition":false,"level":0},{"number":2,"description":"When the user clicks on the mDL doc","duration":1082,"startTime":"2024-10-08T15:58:19.786212+03:00[Europe/Athens]","result":"SUCCESS","precondition":false,"level":0},{"number":3,"description":"Then the mDL should open","duration":924,"startTime":"2024-10-08T15:58:20.869061+03:00[Europe/Athens]","result":"SUCCESS","precondition":false,"level":0},{"number":4,"description":"And the user should see the details of the mDL","duration":909,"startTime":"2024-10-08T15:58:21.794662+03:00[Europe/Athens]","result":"SUCCESS","precondition":false,"level":0}],"userStory":{"id":"ios/regressionTests/view_mdl","storyName":"View mDL document","displayName":"View mDL document","path":"ios/regressionTests/view_mdl","pathElements":[{"name":"ios","description":""},{"name":"regressionTests","description":""},{"name":"view_mdl","description":""}],"type":"feature"},"title":"User opens the mDL document from the dashboard","description":"","tags":[{"name":"US_VMDL_TC_02","type":"tag","displayName":"US_VMDL_TC_02"},{"name":"before_01","type":"tag","displayName":"before_01"},{"name":"Mac","type":"context","displayName":"Mac"},{"name":"US_VMDL","type":"tag","displayName":"US_VMDL"},{"name":"IOS","type":"tag","displayName":"IOS"},{"name":"automated","type":"tag","displayName":"automated"}],"startTime":"2024-10-08T15:57:41.677585+03:00[Europe/Athens]","duration":41028,"projectKey":"","isManualTestingUpToDate":false,"context":"mac","manual":false,"testSource":"Cucumber","order":0,"result":"SUCCESS"}